visual_comet/__init__.py
visual_comet/visualcomet.py
visual_comet/dataloaders/__init__.py
visual_comet/dataloaders/box_utils.py
visual_comet/dataloaders/mask_utils.py
visual_comet/dataloaders/tokenization.py
visual_comet/dataloaders/tokenizers.py
visual_comet/models/__init__.py
visual_comet/models/detector.py
visual_comet/models/detector_feature.py
visual_comet/models/model.py
visual_comet/models/object_detector.py
visual_comet/models/pytorch_misc.py
visualcomet-0.0.11.dist-info/LICENSE
visualcomet-0.0.11.dist-info/METADATA
visualcomet-0.0.11.dist-info/WHEEL
visualcomet-0.0.11.dist-info/dependency_links.txt
visualcomet-0.0.11.dist-info/top_level.txt
visualcomet-0.0.11.dist-info/RECORD
